odoo/addons/fieldservice_crm/README.rst
odoo/addons/fieldservice_crm/__init__.py
odoo/addons/fieldservice_crm/__manifest__.py
odoo/addons/fieldservice_crm/i18n/de.po
odoo/addons/fieldservice_crm/i18n/es.po
odoo/addons/fieldservice_crm/i18n/es_AR.po
odoo/addons/fieldservice_crm/i18n/es_CL.po
odoo/addons/fieldservice_crm/i18n/fieldservice_crm.pot
odoo/addons/fieldservice_crm/i18n/fr.po
odoo/addons/fieldservice_crm/i18n/it.po
odoo/addons/fieldservice_crm/i18n/pt_BR.po
odoo/addons/fieldservice_crm/models/__init__.py
odoo/addons/fieldservice_crm/models/crm_lead.py
odoo/addons/fieldservice_crm/models/fsm_location.py
odoo/addons/fieldservice_crm/models/fsm_order.py
odoo/addons/fieldservice_crm/readme/CONFIGURE.md
odoo/addons/fieldservice_crm/readme/CONTRIBUTORS.md
odoo/addons/fieldservice_crm/readme/CREDITS.md
odoo/addons/fieldservice_crm/readme/DESCRIPTION.md
odoo/addons/fieldservice_crm/readme/INSTALL.md
odoo/addons/fieldservice_crm/readme/ROADMAP.md
odoo/addons/fieldservice_crm/readme/USAGE.md
odoo/addons/fieldservice_crm/security/ir.model.access.csv
odoo/addons/fieldservice_crm/static/description/icon.png
odoo/addons/fieldservice_crm/static/description/index.html
odoo/addons/fieldservice_crm/tests/__init__.py
odoo/addons/fieldservice_crm/tests/test_fsm_crm.py
odoo/addons/fieldservice_crm/views/crm_lead.xml
odoo/addons/fieldservice_crm/views/fsm_location.xml
odoo/addons/fieldservice_crm/views/fsm_order.xml
odoo_addon_fieldservice_crm-18.0.1.0.0.2.dist-info/METADATA
odoo_addon_fieldservice_crm-18.0.1.0.0.2.dist-info/WHEEL
odoo_addon_fieldservice_crm-18.0.1.0.0.2.dist-info/top_level.txt
odoo_addon_fieldservice_crm-18.0.1.0.0.2.dist-info/RECORD
